<?xml version="1.0" encoding="ISO-8859-1" ?>
<DBSCRIPT desc="Esquema UPL">

<SQL db="STOCKDOWN" id="drop etl_movimiento_sku" fails="0" >DROP TABLE etl_movimiento_sku</SQL>
<CREATE_TABLE db="STOCKDOWN" name="etl_movimiento_sku" tablespace="" >
<FIELDS>
<FIELD name="id_documento" fld_type="varchar" length="20" nullable="0" desc="identificador unico del documento de movimiento" primary_key="1"></FIELD>
<FIELD name="id_linea" fld_type="varchar" length="20" nullable="0" desc="identificador unico de la linea del documento de movimiento" primary_key="1"></FIELD>
<FIELD name="tipo_movimiento" fld_type="varchar" length="8" nullable="0" desc="Tipo de movimiento (ingreso, venta, ajuste de inventario, etc)"></FIELD>
<FIELD name="codigo_sku" class="codigo_sku" fld_type="varchar" length="30" nullable="0" desc="Código de SKU asociado al movimiento"></FIELD>
<FIELD name="codigo_centro" fld_type="varchar" length="8" nullable="0" desc="Código de centro asociado al movimiento"></FIELD>
<FIELD name="fecha" fld_type="date" nullable="0" desc="Fecha en que se realizo el movimiento"></FIELD>
<FIELD name="cantidad" fld_type="float" nullable="0" desc="Cantidad de sku movidos"></FIELD>
<FIELD name="tabla_origen" type="varchar" length="50" nullable="1" desc="" /> 
<FIELD name="campo_busqueda" type="varchar" length="50" nullable="1" desc="" /> 
<FIELD name="valor_busqueda" type="varchar" length="100" nullable="1" desc="" />
<FIELD name="clave_ayuda" type="varchar"   length="50"  nullable="1"   ></FIELD>
</FIELDS>
</CREATE_TABLE>
<CREATE_INDEX db="STOCKDOWN" table="etl_movimiento_sku" name="idx_etl_movimiento_sku_01" fields="tabla_origen,campo_busqueda,valor_busqueda" tablespace="" /> 

</DBSCRIPT>